LICENSE.txt
MANIFEST.in
README.rst
setup.cfg
setup.py
data/data_file
rest/__init__.py
rest/grpc_utils.py
rest/mode_utils.py
rest/netconf_utils.py
rest/rest_utils.py
restproject.egg-info/PKG-INFO
restproject.egg-info/SOURCES.txt
restproject.egg-info/dependency_links.txt
restproject.egg-info/entry_points.txt
restproject.egg-info/requires.txt
restproject.egg-info/top_level.txt