Metadata-Version: 1.1
Name: restproject
Version: 0.9
Summary: A rest project
Home-page: https://github.com/pypa/vinapai_restproject
Author: The Python Packaging Authority
Author-email: vinapai@cisco.com
License: MIT
Keywords: sample setuptools development
Platform: UNKNOWN
Classifier: Development Status :: 3 - Alpha
Classifier: Intended Audience :: Developers
Classifier: Topic :: Software Development :: Build Tools
Classifier: License :: OSI Approved :: MIT License
Classifier: Programming Language :: Python :: 3.4
